setup.py
swiffas/__init__.py
swiffas/avm2.py
swiffas/avm2ins.py
swiffas/deserialise.py
swiffas/swfparse.py
swiffas/swftags.py
swiffas.egg-info/PKG-INFO
swiffas.egg-info/SOURCES.txt
swiffas.egg-info/dependency_links.txt
swiffas.egg-info/not-zip-safe
swiffas.egg-info/requires.txt
swiffas.egg-info/top_level.txt