Metadata-Version: 1.0
Name: swiffas
Version: 0.1
Summary: SWF parser and AVM2 (Actionscript 3) bytecode parser
Home-page: http://github.com/ahixon/swiffas
Author: Alex Hixon
Author-email: alex@alexhixon.com
License: MIT
Platform: UNKNOWN
